gitlabds/__init__.py
gitlabds/baselines.py
gitlabds/config_generator.py
gitlabds/dummy.py
gitlabds/feature_reduction.py
gitlabds/insights.py
gitlabds/memory_optimization.py
gitlabds/missing.py
gitlabds/missing_check.py
gitlabds/missing_fill.py
gitlabds/model_evaluator.py
gitlabds/monitoring_metrics.py
gitlabds/outliers.py
gitlabds/split_data.py
gitlabds/trends.py
tests/__init__.py
gitlabds-2.1.7.dist-info/LICENSE
gitlabds-2.1.7.dist-info/METADATA
gitlabds-2.1.7.dist-info/WHEEL
gitlabds-2.1.7.dist-info/top_level.txt
gitlabds-2.1.7.dist-info/RECORD
