Metadata-Version: 2.1
Name: gitlabds
Version: 2.1.7
Summary: Gitlab Data Science and Modeling Tools
Home-page: https://gitlab.com/gitlab-data/gitlabds
Author: Kevin Dietz
Author-email: kdietz@gitlab.com
Classifier: Development Status :: 5 - Production/Stable
Classifier: Intended Audience :: Developers
Classifier: Intended Audience :: Science/Research
Classifier: License :: OSI Approved :: MIT License
Classifier: Programming Language :: Python :: 3
Classifier: Topic :: Scientific/Engineering :: Artificial Intelligence
Classifier: Topic :: Scientific/Engineering :: Information Analysis
Classifier: Topic :: Software Development :: Libraries
Classifier: Topic :: Utilities
Requires-Python: >=3.10
License-File: LICENSE
Requires-Dist: pandas>=1.5.3
Requires-Dist: numpy>=1.23.5
Requires-Dist: scipy>=1.13.1
Requires-Dist: scikit-learn>=1.1.1
Requires-Dist: imbalanced-learn>=0.9.1
Requires-Dist: seaborn>=0.13.2
Requires-Dist: shap>=0.41.0
Requires-Dist: tqdm>=4.66.2
